acers-0.1.0.dist-info/METADATA
acers-0.1.0.dist-info/WHEEL
acers/__init__.py
acers/__init__.pyi
acers/acers.cpython-313-x86_64-linux-gnu.so
acers/py.typed
acers-0.1.0.dist-info/RECORD
